adsocket_transport_django/__init__.py
adsocket_transport_django/activity.py
adsocket_transport_django/apps.py
adsocket_transport_django/creator.py
adsocket_transport_django/exceptions.py
adsocket_transport_django/settings.py
adsocket_transport_django/test.py
adsocket_transport_django/transport.py
adsocket_transport_django/utils.py
adsocket_transport_django/version.py
adsocket_transport_django-0.1.3.dist-info/LICENSE
adsocket_transport_django-0.1.3.dist-info/METADATA
adsocket_transport_django-0.1.3.dist-info/WHEEL
adsocket_transport_django-0.1.3.dist-info/top_level.txt
adsocket_transport_django-0.1.3.dist-info/zip-safe
adsocket_transport_django-0.1.3.dist-info/RECORD
