Metadata-Version: 2.1
Name: adsocket-transport-django
Version: 0.1.3
Summary: ADSocket transport library with Django integration
Home-page: https://github.com/AwesomeDevelopersUG/adsocket-transport-django
Author: Awesome Developers UG
Author-email: support@awesomedevelopers.eu
Maintainer: Awesome Developers UG
Maintainer-email: support@awesomedevelopers.eu
License: MIT
Platform: any
Classifier: Programming Language :: Python :: 3.7
Classifier: Programming Language :: Python :: 3.8
Classifier: License :: OSI Approved :: MIT License
Classifier: Operating System :: OS Independent
Classifier: Development Status :: 4 - Beta
Requires-Dist: adsocket-transport (>=0.1.1)
